{
  "contries": [
    {
      "id": "1",
      "title": "Ukraine",
      "population": "124524623",
      "image": "/src/images/Ukraine.jpg"
    },
    {
      "id": "2",
      "title": "America",
      "population": "7342444232",
      "image": "/public/America.jpg"
    },
    {
      "id": "3",
      "title": "Germany",
      "population": "3563644",
      "image": "/public/Germany.jpg"
    },
    {
      "id": "4",
      "title": "England",
      "population": "945244",
      "image": "/src/images/England.jpg"
    },
    {
      "id": "5",
      "title": "Poland",
      "population": "945244",
      "image": "/src/images/Germany.jpg"
    },
    {
      "id": "2022-08-03T14:00:52.288Z",
      "title": "Hello World"
    },
    {
      "id": "2022-08-03T14:07:43.438Z",
      "title": "Hello World"
    },
    {
      "id": "2022-08-03T14:07:58.691Z",
      "title": "Hello World"
    },
    {
      "id": "2022-08-03T14:09:03.731Z",
      "title": "Hello World"
    },
    {
      "id": "2022-08-03T15:15:25.324Z",
      "title": "Hello World"
    },
    {
      "id": "2022-08-03T15:28:08.181Z",
      "title": "Hello World"
    },
    {
      "id": "2022-08-03T15:45:17.672Z",
      "title": "Hello World"
    },
    {
      "id": "2022-08-03T15:53:20.103Z",
      "title": "Hello World"
    },
    {
      "id": "2022-08-03T15:53:24.580Z",
      "title": "Hello World"
    },
    {
      "id": "2022-08-03T15:54:14.679Z",
      "title": "Hello World"
    },
    {
      "id": "2022-08-03T15:54:57.647Z",
      "title": "Hello World"
    },
    {
      "id": "2022-08-03T16:00:26.139Z",
      "title": "Hello World"
    },
    {
      "id": "2022-08-03T16:01:25.490Z",
      "title": "Hello World"
    },
    {
      "id": "2022-08-03T16:06:40.720Z",
      "title": "Hello World"
    },
    {
      "id": "2022-08-03T16:09:23.659Z",
      "title": "Hello World"
    },
    {
      "id": "2022-08-03T16:09:57.919Z",
      "title": "Hello World"
    },
    {
      "id": "2022-08-03T16:11:18.933Z",
      "title": "Hello World"
    },
    {
      "id": "2022-08-03T16:11:36.417Z",
      "title": "Hello World"
    },
    {
      "id": "2022-08-03T16:14:23.448Z",
      "title": "Hello World"
    },
    {
      "id": "2022-08-03T16:15:38.883Z",
      "title": "Hello World"
    },
    {
      "id": "2022-08-03T16:15:41.623Z",
      "title": "Hello World"
    },
    {
      "id": "2022-08-03T16:16:38.747Z",
      "title": "Hello World"
    },
    {
      "id": "2022-08-03T16:17:23.806Z",
      "title": "Hello World"
    },
    {
      "id": "2022-08-03T16:19:04.137Z",
      "title": "Hello World"
    },
    {
      "id": "2022-08-03T16:22:04.636Z",
      "title": "Hello World"
    },
    {
      "id": "2022-08-03T16:22:05.831Z",
      "title": "Hello World"
    },
    {
      "id": "2022-08-03T16:22:24.888Z",
      "title": "Hello World"
    },
    {
      "id": "2022-08-03T16:22:28.638Z",
      "title": "Hello World"
    },
    {
      "id": "2022-08-03T16:22:36.520Z",
      "title": "Hello World"
    },
    {
      "id": "2022-08-03T16:24:46.574Z",
      "title": "Hello World"
    },
    {
      "id": "2022-08-03T16:27:06.381Z",
      "title": "Hello World"
    },
    {
      "id": "2022-08-03T16:27:09.740Z",
      "title": "Hello World"
    },
    {
      "id": "2022-08-03T16:27:11.591Z",
      "title": "Hello World"
    },
    {
      "id": "2022-08-03T16:27:28.832Z",
      "title": "Hello World"
    }
  ]
}